Metadata-Version: 2.1
Name: embedchaincrewai
Version: 0.1.117
Summary: Simplest open source retrieval (RAG) framework
License: Apache License
Author: Taranjeet Singh
Author-email: taranjeet@embedchain.ai
Requires-Python: >=3.9,<=3.13
Classifier: License :: Other/Proprietary License
Classifier: Programming Language :: Python :: 3
Classifier: Programming Language :: Python :: 3.9
Classifier: Programming Language :: Python :: 3.10
Classifier: Programming Language :: Python :: 3.11
Classifier: Programming Language :: Python :: 3.12
Provides-Extra: aws-bedrock
Provides-Extra: cohere
Provides-Extra: dataloaders
Provides-Extra: discord
Provides-Extra: dropbox
Provides-Extra: elasticsearch
Provides-Extra: github
Provides-Extra: gmail
Provides-Extra: google
Provides-Extra: googledrive
Provides-Extra: huggingface-hub
Provides-Extra: lancedb
Provides-Extra: llama2
Provides-Extra: milvus
Provides-Extra: mistralai
Provides-Extra: modal
Provides-Extra: mysql
Provides-Extra: opensearch
Provides-Extra: opensource
Provides-Extra: poe
Provides-Extra: postgres
Provides-Extra: qdrant
Provides-Extra: rss-feed
Provides-Extra: slack
Provides-Extra: streamlit
Provides-Extra: together
Provides-Extra: vertexai
Provides-Extra: weaviate
Provides-Extra: whatsapp
Provides-Extra: youtube
Requires-Dist: PyGithub (>=1.59.1,<2.0.0) ; extra == "github"
Requires-Dist: alembic (>=1.13.1,<2.0.0)
Requires-Dist: beautifulsoup4 (>=4.12.2,<5.0.0)
Requires-Dist: boto3 (>=1.34.20,<2.0.0) ; extra == "aws-bedrock"
Requires-Dist: chromadb (>=0.4.24,<0.5.0)
Requires-Dist: clarifai (>=10.0.1,<11.0.0)
Requires-Dist: cohere (>=5.3,<6.0) ; extra == "cohere"
Requires-Dist: discord (>=2.3.2,<3.0.0) ; extra == "discord"
Requires-Dist: docx2txt (>=0.8,<0.9) ; extra == "dataloaders"
Requires-Dist: dropbox (>=11.36.2,<12.0.0) ; extra == "dropbox"
Requires-Dist: duckduckgo-search (>=6.1.5,<7.0.0) ; extra == "dataloaders"
Requires-Dist: elasticsearch (>=8.9.0,<9.0.0) ; extra == "elasticsearch"
Requires-Dist: fastapi-poe (==0.0.16) ; extra == "poe"
Requires-Dist: feedparser (>=6.0.10,<7.0.0) ; extra == "rss-feed"
Requires-Dist: flask (>=2.3.3,<3.0.0) ; extra == "slack" or extra == "whatsapp"
Requires-Dist: gitpython (>=3.1.38,<4.0.0) ; extra == "github"
Requires-Dist: google-api-core (>=2.15.0,<3.0.0) ; extra == "gmail"
Requires-Dist: google-api-python-client (>=2.111.0,<3.0.0) ; extra == "gmail" or extra == "googledrive"
Requires-Dist: google-auth (>=2.25.2,<3.0.0) ; extra == "gmail"
Requires-Dist: google-auth-httplib2 (>=0.2.0,<0.3.0) ; extra == "gmail" or extra == "googledrive"
Requires-Dist: google-auth-oauthlib (>=1.2.0,<2.0.0) ; extra == "gmail" or extra == "googledrive"
Requires-Dist: google-cloud-aiplatform (>=1.26.1,<2.0.0)
Requires-Dist: google-generativeai (>=0.3.0,<0.4.0) ; extra == "google"
Requires-Dist: gpt4all (==2.0.2) ; extra == "opensource"
Requires-Dist: gptcache (>=0.1.43,<0.2.0)
Requires-Dist: huggingface_hub (>=0.17.3,<0.18.0) ; extra == "huggingface-hub"
Requires-Dist: lancedb (>=0.6.2,<0.7.0) ; extra == "lancedb"
Requires-Dist: langchain (>0.2,<=0.3)
Requires-Dist: langchain-cohere (>=0.1.4,<0.2.0)
Requires-Dist: langchain-google-vertexai (>=1.0.6,<2.0.0) ; extra == "vertexai"
Requires-Dist: langchain-mistralai (>=0.1.9,<0.2.0) ; extra == "mistralai"
Requires-Dist: langchain-openai (>=0.1.7,<0.2.0)
Requires-Dist: listparser (>=0.19,<0.20) ; extra == "rss-feed"
Requires-Dist: modal (>=0.56.4329,<0.57.0) ; extra == "modal"
Requires-Dist: mysql-connector-python (>=8.1.0,<9.0.0) ; extra == "mysql"
Requires-Dist: newspaper3k (>=0.2.8,<0.3.0) ; extra == "rss-feed"
Requires-Dist: openai (>=1.1.1)
Requires-Dist: opensearch-py (==2.3.1) ; extra == "opensearch"
Requires-Dist: posthog (>=3.0.2,<4.0.0)
Requires-Dist: psycopg (>=3.1.12,<4.0.0) ; extra == "postgres"
Requires-Dist: psycopg-binary (>=3.1.12,<4.0.0) ; extra == "postgres"
Requires-Dist: psycopg-pool (>=3.1.8,<4.0.0) ; extra == "postgres"
Requires-Dist: pymilvus (==2.4.3) ; extra == "milvus"
Requires-Dist: pypdf (>=4.0.1,<5.0.0)
Requires-Dist: pysbd (>=0.3.4,<0.4.0)
Requires-Dist: python-dotenv (>=1.0.0,<2.0.0)
Requires-Dist: pytube (>=15.0.0,<16.0.0) ; extra == "dataloaders"
Requires-Dist: qdrant-client (>=1.6.3,<2.0.0) ; extra == "qdrant"
Requires-Dist: replicate (>=0.15.4,<0.16.0) ; extra == "llama2"
Requires-Dist: requests (>=2.31.0,<3.0.0) ; extra == "gmail"
Requires-Dist: rich (>=13.7.0,<14.0.0)
Requires-Dist: schema (>=0.7.5,<0.8.0)
Requires-Dist: sentence-transformers (>=2.2.2,<3.0.0) ; extra == "opensource" or extra == "dataloaders"
Requires-Dist: slack-sdk (==3.21.3) ; extra == "slack"
Requires-Dist: sqlalchemy (>=2.0.27,<3.0.0)
Requires-Dist: tiktoken (>=0.7.0,<0.8.0)
Requires-Dist: together (>=0.2.8,<0.3.0) ; extra == "together"
Requires-Dist: torch (==2.3.0) ; extra == "opensource"
Requires-Dist: twilio (>=8.5.0,<9.0.0) ; extra == "whatsapp"
Requires-Dist: weaviate-client (>=3.24.1,<4.0.0) ; extra == "weaviate"
Requires-Dist: youtube-transcript-api (>=0.6.1,<0.7.0) ; extra == "dataloaders" or extra == "youtube"
Requires-Dist: yt_dlp (>=2023.11.14,<2024.0.0) ; extra == "youtube"
